pyzdsms/__init__.py
pyzdsms/endpoint.py
pyzdsms/pyzdsms.py
pyzdsms/types.py
pyzdsms-0.0.1.dist-info/LICENSE
pyzdsms-0.0.1.dist-info/METADATA
pyzdsms-0.0.1.dist-info/WHEEL
pyzdsms-0.0.1.dist-info/top_level.txt
pyzdsms-0.0.1.dist-info/RECORD
