Metadata-Version: 2.1
Name: pyzdsms
Version: 0.0.1
Summary: PYZDSMS: Biblioteca para enviar SMS en Cuba con los servicios de ZonaDigital
Home-page: https://github.com/MoonMagiCreation/pyzdsms
Author: Josué Carballo Baños
Author-email: josuecb@yandex.com
License: GPL 3.0
Classifier: Programming Language :: Python :: 3
Classifier: License :: OSI Approved :: GNU General Public License v3 or later (GPLv3+)
Requires-Python: >=3.5
License-File: LICENSE
